lucam/__init__.py
lucam/lucam.py
lucam-2022.9.27.dist-info/LICENSE
lucam-2022.9.27.dist-info/METADATA
lucam-2022.9.27.dist-info/WHEEL
lucam-2022.9.27.dist-info/top_level.txt
lucam-2022.9.27.dist-info/RECORD
