Metadata-Version: 2.1
Name: lucam
Version: 2022.9.27
Summary: Lumenera(r) USB Camera Interface
Home-page: https://www.cgohlke.com
Author: Christoph Gohlke
Author-email: cgohlke@cgohlke.com
License: BSD
Project-URL: Bug Tracker, https://github.com/cgohlke/lucam/issues
Project-URL: Source Code, https://github.com/cgohlke/lucam
Platform: Windows
Classifier: Development Status :: 7 - Inactive
Classifier: License :: OSI Approved :: BSD License
Classifier: Intended Audience :: Science/Research
Classifier: Intended Audience :: Developers
Classifier: Operating System :: Microsoft :: Windows
Classifier: Programming Language :: Python :: 3 :: Only
Classifier: Programming Language :: Python :: 3.7
Classifier: Programming Language :: Python :: 3.8
Classifier: Programming Language :: Python :: 3.9
Classifier: Programming Language :: Python :: 3.10
Classifier: Programming Language :: Python :: 3.11
Requires-Python: >=3.7
License-File: LICENSE
Requires-Dist: numpy (>=1.15.1)
